{
  "posts": [
    {
      "id": 1,
      "title": "hello"
    }
  ],
  "profile": {
    "name": "typicode"
  },
  "productos":[
  {
    "id":1,
    "title":"Senju - Tokyo Revengers",
    "descripcion":"Lorem ipsum dolor sit amet, consectetur adipiscing elit.",
    "precio":1750,
    "img":"https://i.imgur.com/kHfNylw.jpg"
  },
  {
    "id":2,
    "title":"Makima - Chainsaw Man",
    "descripcion":"Lorem ipsum dolor sit amet, consectetur adipiscing elit.",
    "precio":1500,
    "img":"https://i.imgur.com/n4XaxcZ.jpg"
  },
  {
    "id":3,
    "title":"Maki - Jujutsu Kaisen",
    "descripcion":"Lorem ipsum dolor sit amet, consectetur adipiscing elit.",
    "precio":1000,
    "img":"https://i.imgur.com/vvBp0oA.jpg"
  },
  {
    "id":4,
    "title":"Denji - Chainsaw Man",
    "descripcion":"Lorem ipsum dolor sit amet, consectetur adipiscing elit.",
    "precio":1000,
    "img":"https://i.imgur.com/wNk4yDm.jpg"
  },
  {
    "id":5,
    "title":"Rengoku - Kimetsu no Yaiba",
    "descripcion":"Lorem ipsum dolor sit amet, consectetur adipiscing elit.",
    "precio":1000,
    "img":"https://i.imgur.com/xRthSl2.jpg"
  },
  {
    "id":6,
    "title":"Nobara - Jujutsu Kaisen",
    "descripcion":"Lorem ipsum dolor sit amet, consectetur adipiscing elit.",
    "precio":1000,
    "img":"https://i.imgur.com/MQUzzvj.jpg"
  },
  {
    "id":7,
    "title":"Dabi - Boku no Hero",
    "descripcion":"Lorem ipsum dolor sit amet, consectetur adipiscing elit.",
    "precio":1000,
    "img":"https://i.imgur.com/U8SfZjL.jpg"
  },
  {
    "id":8,
    "title":"Levi - Shingeki no Kyojin",
    "descripcion":"Lorem ipsum dolor sit amet, consectetur adipiscing elit.",
    "precio":1000,
    "img":"https://i.imgur.com/6zbcgzf.jpg"
  },
  {
    "id":9,
    "title":"Mikey - Tokyo Revengers",
    "descripcion":"Lorem ipsum dolor sit amet, consectetur adipiscing elit.",
    "precio":1000,
    "img":"https://i.imgur.com/utVor5J.jpg"
  },
  {
    "id":10,
    "title":"Sanemi - Kimetsu no Yaiba",
    "descripcion":"Lorem ipsum dolor sit amet, consectetur adipiscing elit.",
    "precio":1000,
    "img":"https://i.imgur.com/i6eQVK3.jpg"
  },
  {
    "id":11,
    "title":"Gojo Satoru - Jujutsu Kaisen",
    "descripcion":"Lorem ipsum dolor sit amet, consectetur adipiscing elit.",
    "precio":1000,
    "img":"https://i.imgur.com/YF7Dtk5.jpg"
  },
  {
    "id":12,
    "title":"Mikasa - Shingeki no Kyojin",
    "descripcion":"Lorem ipsum dolor sit amet, consectetur adipiscing elit.",
    "precio":1000,
    "img":"https://i.imgur.com/hWVrFRv.jpg"
  }
]
}
